translate_into_chinese/__init__.py
translate_into_chinese/translate_into_chinese.py
translate_into_chinese-1.0.0.dist-info/METADATA
translate_into_chinese-1.0.0.dist-info/WHEEL
translate_into_chinese-1.0.0.dist-info/top_level.txt
translate_into_chinese-1.0.0.dist-info/RECORD
