Metadata-Version: 2.1
Name: translate-into-chinese
Version: 1.0.0
Author: 唐旭东
Requires-Dist: requests
